universal_mcp/cli.py
universal_mcp/config.py
universal_mcp/exceptions.py
universal_mcp/logger.py
universal_mcp/py.typed
universal_mcp/types.py
universal_mcp/applications/application.py
universal_mcp/applications/utils.py
universal_mcp/applications/sample/app.py
universal_mcp/client/oauth.py
universal_mcp/client/token_store.py
universal_mcp/client/transport.py
universal_mcp/integrations/__init__.py
universal_mcp/integrations/integration.py
universal_mcp/servers/__init__.py
universal_mcp/servers/server.py
universal_mcp/stores/__init__.py
universal_mcp/stores/store.py
universal_mcp/tools/__init__.py
universal_mcp/tools/adapters.py
universal_mcp/tools/docstring_parser.py
universal_mcp/tools/func_metadata.py
universal_mcp/tools/local_registry.py
universal_mcp/tools/manager.py
universal_mcp/tools/registry.py
universal_mcp/tools/tools.py
universal_mcp/tools/utils.py
universal_mcp/utils/__init__.py
universal_mcp/utils/installation.py
universal_mcp/utils/prompts.py
universal_mcp/utils/singleton.py
universal_mcp/utils/testing.py
universal_mcp/utils/openapi/__inti__.py
universal_mcp/utils/openapi/api_generator.py
universal_mcp/utils/openapi/api_splitter.py
universal_mcp/utils/openapi/cli.py
universal_mcp/utils/openapi/docgen.py
universal_mcp/utils/openapi/filters.py
universal_mcp/utils/openapi/openapi.py
universal_mcp/utils/openapi/postprocessor.py
universal_mcp/utils/openapi/preprocessor.py
universal_mcp/utils/openapi/readme.py
universal_mcp/utils/openapi/test_generator.py
universal_mcp/utils/templates/README.md.j2
universal_mcp/utils/templates/api_client.py.j2
universal_mcp-0.1.24.dist-info/METADATA
universal_mcp-0.1.24.dist-info/WHEEL
universal_mcp-0.1.24.dist-info/entry_points.txt
universal_mcp-0.1.24.dist-info/licenses/LICENSE
universal_mcp-0.1.24.dist-info/RECORD
